vellum_cli/CONTRIBUTING.md
vellum_cli/README.md
vellum_cli/__init__.py
vellum_cli/aliased_group.py
vellum_cli/config.py
vellum_cli/image_push.py
vellum_cli/init.py
vellum_cli/logger.py
vellum_cli/ping.py
vellum_cli/pull.py
vellum_cli/push.py
vellum_cli/tests/__init__.py
vellum_cli/tests/conftest.py
vellum_cli/tests/test_config.py
vellum_cli/tests/test_image_push.py
vellum_cli/tests/test_image_push_error_handling.py
vellum_cli/tests/test_init.py
vellum_cli/tests/test_main.py
vellum_cli/tests/test_ping.py
vellum_cli/tests/test_pull.py
vellum_cli/tests/test_push.py
vellum_ee/__init__.py
vellum_ee/py.typed
vellum_ee/workflows/__init__.py
vellum_ee/workflows/display/__init__.py
vellum_ee/workflows/display/base.py
vellum_ee/workflows/display/editor/__init__.py
vellum_ee/workflows/display/editor/types.py
vellum_ee/workflows/display/exceptions.py
vellum_ee/workflows/display/nodes/__init__.py
vellum_ee/workflows/display/nodes/base_node_display.py
vellum_ee/workflows/display/nodes/get_node_display_class.py
vellum_ee/workflows/display/nodes/tests/__init__.py
vellum_ee/workflows/display/nodes/tests/test_base_node_display.py
vellum_ee/workflows/display/nodes/types.py
vellum_ee/workflows/display/nodes/utils.py
vellum_ee/workflows/display/nodes/vellum/__init__.py
vellum_ee/workflows/display/nodes/vellum/api_node.py
vellum_ee/workflows/display/nodes/vellum/base_adornment_node.py
vellum_ee/workflows/display/nodes/vellum/code_execution_node.py
vellum_ee/workflows/display/nodes/vellum/conditional_node.py
vellum_ee/workflows/display/nodes/vellum/error_node.py
vellum_ee/workflows/display/nodes/vellum/final_output_node.py
vellum_ee/workflows/display/nodes/vellum/guardrail_node.py
vellum_ee/workflows/display/nodes/vellum/inline_prompt_node.py
vellum_ee/workflows/display/nodes/vellum/inline_subworkflow_node.py
vellum_ee/workflows/display/nodes/vellum/map_node.py
vellum_ee/workflows/display/nodes/vellum/merge_node.py
vellum_ee/workflows/display/nodes/vellum/note_node.py
vellum_ai-1.2.4.dist-info/LICENSE
vellum_ai-1.2.4.dist-info/METADATA
vellum_ai-1.2.4.dist-info/WHEEL
vellum_ai-1.2.4.dist-info/entry_points.txt
vellum_ai-1.2.4.dist-info/RECORD
