Metadata-Version: 2.1
Name: vellum-ai
Version: 1.2.4
Summary: 
License: MIT
Requires-Python: >=3.9,<4.0
Classifier: Intended Audience :: Developers
Classifier: License :: OSI Approved :: MIT License
Classifier: Operating System :: MacOS
Classifier: Operating System :: Microsoft :: Windows
Classifier: Operating System :: OS Independent
Classifier: Operating System :: POSIX
Classifier: Operating System :: POSIX :: Linux
Classifier: Programming Language :: Python
Classifier: Programming Language :: Python :: 3
Classifier: Programming Language :: Python :: 3.9
Classifier: Programming Language :: Python :: 3.10
Classifier: Programming Language :: Python :: 3.11
Classifier: Programming Language :: Python :: 3.12
Classifier: Programming Language :: Python :: 3.8
Classifier: Topic :: Software Development :: Libraries :: Python Modules
Classifier: Typing :: Typed
Requires-Dist: Jinja2 (>=3.1.0,<4.0.0)
Requires-Dist: click (>=8.1.7,<9.0.0)
Requires-Dist: docker (>=7.1.0,<8.0.0)
Requires-Dist: httpx (>=0.21.2)
Requires-Dist: openai (>=1.0.0,<2.0.0)
Requires-Dist: orderly-set (>=5.2.2,<6.0.0)
Requires-Dist: publication (==0.0.3)
Requires-Dist: pydantic (>=1.9.2)
Requires-Dist: pydantic-core (>=2.18.2)
Requires-Dist: pydash (>=7.0.0,<8.0.0)
Requires-Dist: python-dateutil (>=2.8.0,<3.0.0)
Requires-Dist: python-dotenv (>=1.0.0,<2.0.0)
Requires-Dist: pytz (>=2022.0,<2026.0)
Requires-Dist: pyyaml (>=6.0.0,<7.0.0)
Requires-Dist: requests (>=2.31.0,<3.0.0)
Requires-Dist: tomli (>=2.0.0,<3.0.0)
Requires-Dist: typing_extensions (>=4.0.0)
Project-URL: Repository, https://github.com/vellum-ai/vellum-python-sdks
